fedexrates
